clockify/Clockify.py
clockify/__init__.py
pyclockify-0.1.0.dist-info/METADATA
pyclockify-0.1.0.dist-info/WHEEL
pyclockify-0.1.0.dist-info/top_level.txt
pyclockify-0.1.0.dist-info/RECORD
