Metadata-Version: 2.1
Name: pyclockify
Version: 0.1.0
Summary: Python library for interacting with the Clockify API
Author: Alejandro Santiago Félix
Author-email: alex.0002002@gmail.com
Classifier: Development Status :: 3 - Alpha
Classifier: Intended Audience :: Developers
Classifier: License :: OSI Approved :: MIT License
Classifier: Programming Language :: Python :: 3
Classifier: Programming Language :: Python :: 3.6
Classifier: Programming Language :: Python :: 3.7
Classifier: Programming Language :: Python :: 3.8
Classifier: Programming Language :: Python :: 3.9
Requires-Dist: requests
Requires-Dist: attrs
